gimu/__init__.py
gimu/config.py
gimu/easy_date.py
gimu/geo_common.py
gimu/project_cli.py
gimu/save2incon.py
gimu/t2listingh5.py
gimu/waiwera_copy.py
gimu/waiwera_listing.py
gimu/gmf/__init__.py
gimu/gmf/data.py
gimu-0.2.0.dist-info/METADATA
gimu-0.2.0.dist-info/WHEEL
gimu-0.2.0.dist-info/entry_points.txt
gimu-0.2.0.dist-info/licenses/LICENSE.txt
gimu-0.2.0.dist-info/RECORD
