Metadata-Version: 2.4
Name: gimu
Version: 0.2.0
Summary: A toolkit and python library for modelling at Geothermal Institute, University of Auckland.
Project-URL: Documentation, https://github.com/cyeh015/gimu/blob/main/README.md
Project-URL: Issues, https://github.com/cyeh015/gimu/issues
Project-URL: Source, https://github.com/cyeh015/gimu
Author-email: Angus Yeh <a.yeh@auckland.ac.nz>
License-Expression: MIT
License-File: LICENSE.txt
Classifier: Development Status :: 4 - Beta
Classifier: Programming Language :: Python
Classifier: Programming Language :: Python :: 3.8
Classifier: Programming Language :: Python :: 3.9
Classifier: Programming Language :: Python :: 3.10
Classifier: Programming Language :: Python :: 3.11
Classifier: Programming Language :: Python :: Implementation :: CPython
Classifier: Programming Language :: Python :: Implementation :: PyPy
Requires-Python: >=3.8
Requires-Dist: h5py
Requires-Dist: matplotlib
Requires-Dist: numpy
Requires-Dist: pint
Requires-Dist: pytough
Requires-Dist: scipy
